{
  "project_info": {
    "project_number": "438378191753",
    "firebase_url": "https://olevpush-d9d2f.firebaseio.com",
    "project_id": "olevpush-d9d2f",
    "storage_bucket": "olevpush-d9d2f.appspot.com"
  },
  "client": [
    {
      "client_info": {
        "mobilesdk_app_id": "1:438378191753:android:a50ea0ce204e682fbf5f58",
        "android_client_info": {
          "package_name": "ac.kr.olev"
        }
      },
      "oauth_client": [
        {
          "client_id": "438378191753-9a9t4g5u24b6lg4ra3csdb5r6hsjnn3p.apps.googleusercontent.com",
          "client_type": 3
        }
      ],
      "api_key": [
        {
          "current_key": "AIzaSyCCo60-DFpvdy3fvjbKXYgfP-dnzLWhv2M"
        }
      ],
      "services": {
        "appinvite_service": {
          "other_platform_oauth_client": [
            {
              "client_id": "438378191753-9a9t4g5u24b6lg4ra3csdb5r6hsjnn3p.apps.googleusercontent.com",
              "client_type": 3
            }
          ]
        }
      }
    },
    {
      "client_info": {
        "mobilesdk_app_id": "1:438378191753:android:1e540e459c850155bf5f58",
        "android_client_info": {
          "package_name": "com.umls.invertergpskaist"
        }
      },
      "oauth_client": [
        {
          "client_id": "438378191753-9a9t4g5u24b6lg4ra3csdb5r6hsjnn3p.apps.googleusercontent.com",
          "client_type": 3
        }
      ],
      "api_key": [
        {
          "current_key": "AIzaSyCCo60-DFpvdy3fvjbKXYgfP-dnzLWhv2M"
        }
      ],
      "services": {
        "appinvite_service": {
          "other_platform_oauth_client": [
            {
              "client_id": "438378191753-9a9t4g5u24b6lg4ra3csdb5r6hsjnn3p.apps.googleusercontent.com",
              "client_type": 3
            }
          ]
        }
      }
    }
  ],
  "configuration_version": "1"
}